seedsim/__init__.py
seedsim/compiler/Compiler.py
seedsim/compiler/DistributedDocker.py
seedsim/compiler/Docker.py
seedsim/compiler/GcpDistributedDocker.py
seedsim/compiler/Graphviz.py
seedsim/compiler/__init__.py
seedsim/core/AddressAssignmentConstraint.py
seedsim/core/AutonomousSystem.py
seedsim/core/Graphable.py
seedsim/core/InternetExchange.py
seedsim/core/Network.py
seedsim/core/Node.py
seedsim/core/Printable.py
seedsim/core/Registry.py
seedsim/core/__init__.py
seedsim/core/enums.py
seedsim/layers/Base.py
seedsim/layers/CymruIpOrigin.py
seedsim/layers/Dnssec.py
seedsim/layers/DomainNameCachingService.py
seedsim/layers/DomainNameService.py
seedsim/layers/Ebgp.py
seedsim/layers/Ibgp.py
seedsim/layers/Layer.py
seedsim/layers/Mpls.py
seedsim/layers/Ospf.py
seedsim/layers/Reality.py
seedsim/layers/ReverseDomainNameService.py
seedsim/layers/Routing.py
seedsim/layers/RpkiService.py
seedsim/layers/Service.py
seedsim/layers/WebService.py
seedsim/layers/__init__.py
seedsim/renderer/Renderer.py
seedsim/renderer/__init__.py
seedsim-0.0.7.dist-info/LICENSE
seedsim-0.0.7.dist-info/METADATA
seedsim-0.0.7.dist-info/WHEEL
seedsim-0.0.7.dist-info/top_level.txt
seedsim-0.0.7.dist-info/RECORD
