Metadata-Version: 2.1
Name: seedsim
Version: 0.0.7
Summary: SEED Internet Simulator
Home-page: https://github.com/seed-labs/seed-simulator
Author: Honghao Zeng
Author-email: hozeng@syr.edu
License: UNKNOWN
Platform: UNKNOWN
Classifier: Programming Language :: Python :: 3
Classifier: License :: OSI Approved :: MIT License
Classifier: Operating System :: OS Independent
Requires-Python: >=3.6
Requires-Dist: requests
